Metadata-Version: 2.1
Name: investingscraper
Version: 0.0.5
Summary: Developed by SamedZZZZ
Home-page: UNKNOWN
Author: SamedZZZZ
Author-email: zirhlioglusamed@gmail.com
License: MIT
Keywords: investing
Platform: UNKNOWN
Classifier: Development Status :: 2 - Pre-Alpha
Classifier: License :: OSI Approved :: MIT License
Classifier: Programming Language :: Python :: 3
Classifier: Operating System :: Microsoft :: Windows :: Windows 10
Classifier: Environment :: Console
Classifier: Intended Audience :: Financial and Insurance Industry
License-File: LICENSE.md
